mj_package/__init__.py
mj_package/mj_package1.py
mj_package/mj_package2.py
mj_package_ipc/__init__.py
mj_package_ipc/mj_package1.py
mj_package_ipc/mj_package2.py
mj_package_ipc-0.1.0.dist-info/METADATA
mj_package_ipc-0.1.0.dist-info/WHEEL
mj_package_ipc-0.1.0.dist-info/licence
mj_package_ipc-0.1.0.dist-info/top_level.txt
mj_package_ipc-0.1.0.dist-info/RECORD
