Metadata-Version: 2.1
Name: mj-package-ipc
Version: 0.1.0
Summary: Example Python package
Home-page: 
Author: Madhusudan J
Author-email: madhusudanj021vl@gmil.com
Classifier: Programming Language :: Python :: 3.11
License-File: licence
Requires-Dist: numpy
